mypackage/__init__.py
mypackage/math_utils.py
mypackage/string_utils.py
mypackage/helpers/__init__.py
mypackage/helpers/date_utils.py
abhaykipavbhaji-0.1.0.dist-info/METADATA
abhaykipavbhaji-0.1.0.dist-info/WHEEL
abhaykipavbhaji-0.1.0.dist-info/top_level.txt
abhaykipavbhaji-0.1.0.dist-info/RECORD
