Metadata-Version: 2.4
Name: abhaykipavbhaji
Version: 0.1.0
Summary: A sample pip-installable package with multiple modules
Author: Abhay
Author-email: Your Name <your@email.com>
Requires-Python: >=3.7
Dynamic: author
Dynamic: requires-python
